yuanfen/__init__.py
yuanfen/config.py
yuanfen/email.py
yuanfen/env.py
yuanfen/group_robot.py
yuanfen/hash.py
yuanfen/ip.py
yuanfen/logger.py
yuanfen/redis.py
yuanfen/response.py
yuanfen/sms.py
yuanfen/time.py
yuanfen/version.py
yuanfen-2025.11.10.2.dist-info/licenses/LICENSE
yuanfen-2025.11.10.2.dist-info/METADATA
yuanfen-2025.11.10.2.dist-info/WHEEL
yuanfen-2025.11.10.2.dist-info/top_level.txt
yuanfen-2025.11.10.2.dist-info/RECORD
