Metadata-Version: 2.4
Name: yuanfen
Version: 2025.11.10.2
Summary: Yuanfen Python Library
Author-email: Bean <bean@yuanfen.net>
License: MIT
Project-URL: repository, https://github.com/YuanfenNet/yf-lib-py
Classifier: License :: OSI Approved :: MIT License
Classifier: Operating System :: OS Independent
Classifier: Programming Language :: Python :: 3
Classifier: Programming Language :: Python
Requires-Python: >=3.9
License-File: LICENSE
Requires-Dist: alibabacloud-dysmsapi20170525~=4.2.0
Requires-Dist: chardet~=5.2
Requires-Dist: pydantic~=2.10
Requires-Dist: pytz~=2025.1
Requires-Dist: pyyaml~=6.0
Requires-Dist: redis~=7.0
Requires-Dist: requests~=2.0
Requires-Dist: watchdog~=6.0
Dynamic: license-file
